blastengine/Bulk.py
blastengine/Client.py
blastengine/Job.py
blastengine/Log.py
blastengine/Mail.py
blastengine/MailBase.py
blastengine/Transaction.py
blastengine/__init__.py
blastengine-0.0.7.dist-info/LICENSE
blastengine-0.0.7.dist-info/METADATA
blastengine-0.0.7.dist-info/WHEEL
blastengine-0.0.7.dist-info/top_level.txt
blastengine-0.0.7.dist-info/RECORD
