Metadata-Version: 2.1
Name: blastengine
Version: 0.0.7
Summary: blastengine is SDK for blastengine
Home-page: https://blastengine.jp/
Author: goofmint
Author-email: atsushi@moongift.jp
Classifier: Programming Language :: Python :: 3.8
Classifier: License :: OSI Approved :: MIT License
Classifier: Operating System :: OS Independent
License-File: LICENSE
Requires-Dist: requests
